CHANGES.txt
MANIFEST.in
setup.cfg
setup.py
src/img2ply.py
src/img2ply.egg-info/PKG-INFO
src/img2ply.egg-info/SOURCES.txt
src/img2ply.egg-info/dependency_links.txt
src/img2ply.egg-info/entry_points.txt
src/img2ply.egg-info/requires.txt
src/img2ply.egg-info/top_level.txt