Metadata-Version: 1.1
Name: img2ply
Version: 0.1.1
Summary: Convert an image sequence to a PLY point cloud.
Home-page: https://github.com/robertjoosten/img2ply
Author: Robert Joosten
Author-email: rwm.joosten@gmail.com
License: GNU General Public License v3.0
Download-URL: https://github.com/robertjoosten/img2ply/archive/0.1.1.tar.gz
Keywords: image ply converter
Platform: UNKNOWN
